My_passman-0.0.5.data/scripts/Pass_man.py
scripts/AES256.py
scripts/Authhandler.py
scripts/Pass_man.py
scripts/__init__.py
scripts/hash.py
My_passman-0.0.5.dist-info/LICENCE
My_passman-0.0.5.dist-info/METADATA
My_passman-0.0.5.dist-info/WHEEL
My_passman-0.0.5.dist-info/entry_points.txt
My_passman-0.0.5.dist-info/top_level.txt
My_passman-0.0.5.dist-info/RECORD
